pythagix/__init__.py
pythagix/figurates.py
pythagix/fraction.py
pythagix/numbering.c
pythagix/numbering.cp313-win_amd64.pyd
pythagix/pnumbering.py
pythagix/pprime.py
pythagix/prime.c
pythagix/prime.cp313-win_amd64.pyd
pythagix/pstat.py
pythagix/ratio.c
pythagix/ratio.cp313-win_amd64.pyd
pythagix/stat.c
pythagix/stat.cp313-win_amd64.pyd
pythagix/tempCodeRunnerFile.py
pythagix-0.2.23.dist-info/licenses/LICENSE
pythagix-0.2.23.dist-info/METADATA
pythagix-0.2.23.dist-info/WHEEL
pythagix-0.2.23.dist-info/top_level.txt
pythagix-0.2.23.dist-info/RECORD
