Metadata-Version: 2.4
Name: pythagix
Version: 0.2.23
Summary: Pythagix is a lightweight Python library that provides a collection of mathematical utility functions for number theory
Author: UltraQuantumScriptor
License: MIT
Project-URL: Homepage, https://github.com/UltraQuantumScriptor/pythagix
Project-URL: Source, https://github.com/UltraQuantumScriptor/pythagix
Project-URL: Bug Tracker, https://github.com/UltraQuantumScriptor/pythagix/issues
Keywords: math,prime,LCM,triangle numbers,gcd,statistics,utilities,high-digit math
Classifier: Programming Language :: Python :: 3
Classifier: License :: OSI Approved :: MIT License
Requires-Python: >=3.6
License-File: LICENSE
Dynamic: license-file
Dynamic: requires-python
